commandfile/__init__.py
commandfile/argparse.py
commandfile/io.py
commandfile/model.py
commandfile/model_generated.py
commandfile/data/schema.json
commandfile-0.2.0.dist-info/licenses/LICENSE
commandfile-0.2.0.dist-info/METADATA
commandfile-0.2.0.dist-info/WHEEL
commandfile-0.2.0.dist-info/top_level.txt
commandfile-0.2.0.dist-info/RECORD
