Metadata-Version: 2.4
Name: commandfile
Version: 0.2.0
Summary: Command file for scientific workflows.
License-Expression: Apache-2.0
Requires-Python: >=3.11
License-File: LICENSE
Requires-Dist: pydantic
Requires-Dist: pyyaml
Dynamic: license-file
